fabkit/__init__.py
fabkit/files.py
fabkit/sudoer.py
fabkit/system.py
fabkit/systemd.py
fabkit/template.py
fabkit/ufw.py
fabkit/user.py
fabkit/util.py
fabkit/arch/__init__.py
fabkit/arch/manager.py
fabkit-0.4.0.dist-info/METADATA
fabkit-0.4.0.dist-info/RECORD
fabkit-0.4.0.dist-info/WHEEL
fabkit-0.4.0.dist-info/top_level.txt
fabkit-0.4.0.dist-info/zip-safe
