Metadata-Version: 2.1
Name: fabkit
Version: 0.4.0
Summary: Group of tools extending fabric v1.x tasks
Home-page: https://github.com/karolhor/fabkit
Author: Karol Horowski
Author-email: karol.hor@gmail.com
License: MIT
Platform: UNKNOWN
Classifier: Development Status :: 3 - Alpha
Classifier: Environment :: Console
Classifier: Intended Audience :: Developers
Classifier: Intended Audience :: System Administrators
Classifier: License :: OSI Approved :: MIT License
Classifier: Operating System :: MacOS
Classifier: Operating System :: POSIX
Classifier: Operating System :: Unix
Classifier: Programming Language :: Python :: 3 :: Only
Classifier: Programming Language :: Python :: 3.6
Classifier: Programming Language :: Python :: 3.7
Classifier: Topic :: Software Development
Classifier: Topic :: Software Development :: Build Tools
Classifier: Topic :: Software Development :: Libraries
Classifier: Topic :: System :: Systems Administration
Requires-Python: >=3.6
Requires-Dist: fabric3 (>=1.7.0)
Requires-Dist: jinja2
